zencoreipinfo.py
zencoreipinfo-0.1.0.dist-info/LICENSE
zencoreipinfo-0.1.0.dist-info/METADATA
zencoreipinfo-0.1.0.dist-info/WHEEL
zencoreipinfo-0.1.0.dist-info/entry_points.txt
zencoreipinfo-0.1.0.dist-info/top_level.txt
zencoreipinfo-0.1.0.dist-info/RECORD
